{
  "categories": "Mukbang",
  "audience_target": [
    "Học sinh, sinh viên",
    "Người trẻ (Gen Z)",
    "Người thích ăn vặt, đồ ngọt"
  ],
  "body_analysis": [
    {
      "step": "Giới thiệu món ăn",
      "desc": "Út giới thiệu món phô mai que kèm các loại sốt và dưa leo.",
      "impact_level": "2",
      "viewer_emotion": "Tò mò về hương vị món ăn."
    },
    {
      "step": "Bắt đầu ăn",
      "desc": "Út bắt đầu ăn phô mai que chiên giòn chấm cùng tương ớt, mayonnaise.",
      "impact_level": "2",
      "viewer_emotion": "Hơi đói bụng và thèm ăn."
    },
    {
      "step": "Miêu tả hương vị",
      "desc": "Nhận xét phô mai que thơm, béo; thắc mắc không thấy sợi phô mai.",
      "impact_level": "2",
      "viewer_emotion": "Tập trung vào cảm nhận hương vị."
    },
    {
      "step": "Kết hợp với dưa leo",
      "desc": "Ăn kèm dưa leo để đỡ ngấy và tăng thêm hương vị.",
      "impact_level": "2",
      "viewer_emotion": "Thấy có vẻ hợp lý và ngon miệng."
    }
  ],
  "content_style": [
    "Đời thường",
    "Nhanh gọn"
  ],
  "cta_content": [],
  "cta_type": [],
  "emotion_keywords": [
    "thơm",
    "béo",
    "đỡ ngấy"
  ],
  "has_cta": "false",
  "highlight_phrases": [
    "Mới chiên xong ở ngoài nó sẽ thơm mùi phô mai lắm nha mọi người.",
    "Thơm thơm béo béo."
  ],
  "hook_content": "Mời mọi người ăn cùng Út nhen. Hôm nay Út sẽ ăn phô mai que nha.",
  "hook_type": [
    "Vào thẳng vấn đề"
  ],
  "pacing": [
    "Chậm"
  ],
  "structure_style": [
    "Chia sẻ trải nghiệm cá nhân"
  ],
  "summarization": "Video ghi lại cảnh Út Phụng Kim ăn phô mai que chiên giòn chấm cùng tương ớt, mayonnaise và ăn kèm dưa leo để đỡ ngấy. Út nhận xét phô mai thơm, béo nhưng không thấy sợi phô mai.",
  "tone_of_voice": [
    "Thân thiện"
  ]
}