{
  "categories": "Review quán ăn",
  "audience_target": [
    "Người trẻ (Gen Z)",
    "Người thích ăn vặt, đồ ngọt"
  ],
  "body_analysis": [
    {
      "step": "Giới thiệu sản phẩm",
      "desc": "Giới thiệu gói Lays khổng lồ, snack Lays và set ăn Haidilao.",
      "impact_level": "2",
      "viewer_emotion": "Thích thú vì sự hấp dẫn của các món ăn."
    },
    {
      "step": "Thông báo chương trình khuyến mãi",
      "desc": "Thông báo chương trình khuyến mãi khi đến Haidilao BTesco.",
      "impact_level": "2",
      "viewer_emotion": "Tò mò về cách tham gia chương trình."
    },
    {
      "step": "Hướng dẫn tham gia",
      "desc": "Hướng dẫn order bàn ăn, đọc mật ngữ và quay review.",
      "impact_level": "2",
      "viewer_emotion": "Cảm thấy chương trình khá đơn giản và dễ tham gia."
    },
    {
      "step": "Nhấn mạnh lợi ích",
      "desc": "Nhấn mạnh việc vừa được ăn ngon vừa có quà mang về.",
      "impact_level": "3",
      "viewer_emotion": "Vô cùng hứng thú với lợi ích của chương trình."
    },
    {
      "step": "Kêu gọi tham gia sớm",
      "desc": "Kêu gọi rủ team đi sớm vì số lượng quà có hạn.",
      "impact_level": "2",
      "viewer_emotion": "Sốt sắng vì sợ hết quà."
    }
  ],
  "content_style": [
    "Gen Z",
    "Đời thường",
    "Nhanh gọn"
  ],
  "cta_content": [
    "Các ông mấy bà chỉ cần đến ngay Hai Gi rau BTesco và order một bàn ăn 600 cành hoa và đọc mật ngữ. Lay, giòn giòn ngon ngon cuốn ơi là cuốn.",
    "Khi đọc mật ngữ xong thì mấy ông mấy bà nhớ quay review chung với lại gói ôm Lays khổng lồ nhen. Lên mạng xã hội và kèm với lại hashtag tôi đang gắn ở trên màn hình."
  ],
  "cta_type": [
    "Ghé thăm địa điểm",
    "Ăn cùng",
    "Chia sẻ"
  ],
  "emotion_keywords": [
    "ngon",
    "thích"
  ],
  "has_cta": "true",
  "highlight_phrases": [
    "Lay, giòn giòn ngon ngon cuốn ơi là cuốn",
    "Team nào mà mê snack khoai tây Lays với lẩu là không thể nào bỏ qua cái chương trình này đâu á nhen.",
    "Vừa được ăn ngon mà vừa có quà đem về nữa, thích quá trời thích luôn."
  ],
  "hook_content": "hai rau ơi. Dạ em nghe à. Lay, giòn giòn ngon ngon cuốn ơi là cuốn.",
  "hook_type": [
    "Vào thẳng vấn đề",
    "Khuyến mãi"
  ],
  "pacing": [
    "Nhanh"
  ],
  "structure_style": [
    "Mô tả đặc điểm",
    "Chia sẻ trải nghiệm cá nhân",
    "Hướng dẫn"
  ],
  "summarization": "Video giới thiệu chương trình khuyến mãi đặc biệt tại Haidilao BTesco khi order bàn ăn 600k và đọc mật ngữ sẽ nhận được nhiều quà hấp dẫn từ Lay's. Video kêu gọi người xem nhanh chóng rủ bạn bè đến tham gia để không bỏ lỡ cơ hội.",
  "tone_of_voice": [
    "Hào hứng",
    "Thân thiện"
  ]
}