{
  "category": ["Nấu ăn"],
  "main_content_focus": ["Món ăn", "Công thức nấu ăn", "Cảm nhận trải nghiệm"],
  "structure_style": ["Hướng dẫn", "Review trải nghiệm", "Kể chuyện"],
  "hook_type": ["Kể chuyện", "Vào thẳng vấn đề"],
  "tone_of_voice": ["Thân mật", "Hào hứng"],
  "pacing": ["Chậm"],
  "has_cta": true,
  "cta_type": ["Comment"],
  "emotion_keywords": ["mát mẻ", "xanh tươi", "thích", "ngon", "hiếu khách", "hào sản", "nhiệt tình"],
  "hook_content": "được dịp nghỉ tết dương lịch nên xuống nhà bạn hương miền tây chơi, theo lời mời lần trước khi hương lên thăm chòi lá của tuấn.",
  "cta_phrases": ["để coi gần tết đi đâu vui, cả nhà gợi ý giúp tuấn nha."],
  "highlight_phrases": ["cá tra nhúng giấm", "mập củn củn luôn, sớ thịt nhìn thấy ham", "người miền tây hiếu khách hào sản, quả không sai"],
  "notable_elements": ["Video mang tính chất đời thường, gần gũi", "Cách dẫn chuyện tự nhiên, không gò bó", "Nội dung tập trung vào trải nghiệm nấu ăn và giao lưu văn hóa"],
  "gemini_analysis": "Video có bố cục rõ ràng, bắt đầu bằng việc giới thiệu chuyến đi, sau đó tập trung vào quá trình chuẩn bị và thưởng thức món ăn. Cách kể chuyện chân thật và gần gũi giúp tạo sự kết nối với người xem. Tuy nhiên, video có thể thêm các cảnh quay cận cảnh hơn về món ăn để tăng tính hấp dẫn."
}