{
  "category": ["Nấu ăn"],
  "main_content_focus": ["Món ăn"],
  "structure_style": ["Hướng dẫn"],
  "hook_type": ["Vào thẳng vấn đề"],
  "tone_of_voice": ["Hào hứng", "Thân mật"],
  "pacing": ["Nhanh"],
  "has_cta": false,
  "cta_type": [],
  "emotion_keywords": ["tươi", "thơm", "ngon"],
  "hook_content": "sò huyết cồ xào khủng răng me. bữa nay tấn sẽ làm đại tiệc hải sản nha cả nhà.",
  "cta_phrases": [],
  "highlight_phrases": ["đại tiệc hải sản", "cua lông đầu mùa", "mấy con ốc gai này nó lát hết trước", "ốc gai khổng lồ"],
  "notable_elements": ["Nhiều loại hải sản lạ", "Cách chế biến đa dạng", "Giọng nói thân thiện, gần gũi"],
  "gemini_analysis": "Video thể hiện quá trình chuẩn bị và chế biến nhiều món hải sản khác nhau. Sự đa dạng của các món ăn có thể thu hút người xem, đặc biệt là những người yêu thích hải sản. Giọng văn thân thiện giúp tạo cảm giác gần gũi."
}