{
  "category": ["Review sản phẩm ăn uống"],
  "main_content_focus": ["Sản phẩm ăn uống", "Cảm nhận trải nghiệm"],
  "structure_style": ["Review trải nghiệm"],
  "hook_type": ["Vào thẳng vấn đề"],
  "tone_of_voice": ["Hào hứng", "Thân mật"],
  "pacing": ["Nhanh"],
  "has_cta": false,
  "cta_type": [],
  "emotion_keywords": ["thơm", "hấp dẫn", "ngậy ngậy", "béo béo", "cuốn", "giòn", "cay cay", "ngậy", "béo", "giòn rần rật"],
  "hook_content": "ưm. mọi người ơi nay cô ta siêu thèm cả bệnh taco, nên là cô ta đã đặt ship ở bên taco nón lá về để ăn nha.",
  "cta_phrases": [],
  "highlight_phrases": ["trông nó quá là hấp dẫn", "siêu to luôn", "toàn topping là topping bên trong thôi", "vị nó rất là hòa quyện ngậy ngậy béo béo", "ăn rất là cuốn luôn ý", "giòn rần rật rần rật rất là cuốn nha"],
  "notable_elements": ["Cách xưng hô 'cô ta' tạo sự gần gũi, hài hước", "Nhấn mạnh vào cảm xúc thèm thuồng khi mở đầu"],
  "gemini_analysis": "Video có cách dẫn dắt tự nhiên, gần gũi, tạo cảm giác thân thiện cho người xem. Việc tập trung vào cảm xúc thèm ăn và mô tả chi tiết các món ăn giúp video trở nên hấp dẫn. Tuy nhiên, video thiếu lời kêu gọi hành động (CTA) để tăng tương tác."
}