{
  "categories": [
    "Review sản phẩm ăn uống",
    "Review món ăn"
  ],
  "audience_target": [
    "Học sinh, sinh viên",
    "Người trẻ (Gen Z)",
    "Người thích ăn vặt, đồ ngọt"
  ],
  "body_analysis": [
    {
      "step": "Giới thiệu sản phẩm",
      "comment": "So sánh sản phẩm bột pha bò húc với bò húc thật."
    },
    {
      "step": "Pha chế và so sánh màu sắc",
      "comment": "Nhận xét về màu sắc khác biệt giữa hai loại nước."
    },
    {
      "step": "Đánh giá mùi vị",
      "comment": "So sánh mùi vị và cảm nhận về chất lượng của bột pha."
    },
    {
      "step": "So sánh với bò húc thật",
      "comment": "Khẳng định sự khác biệt và đánh giá cao bò húc thật."
    },
    {
      "step": "Tổng kết",
      "comment": "Nhấn mạnh lại về vị ngọt và mùi hóa học của bột pha, đưa ra lời khuyên."
    }
  ],
  "content_style": [
    "Đời thường",
    "Nhanh gọn"
  ],
  "cta_content": [
    "Uống cái này thì uống chơi uống vui, chứ còn mình nghĩ cái này không nên uống nhiều."
  ],
  "cta_type": [
    "Đặt câu hỏi"
  ],
  "emotion_keywords": [
    "ngọt",
    "hơi đẻo",
    "hơi kỳ kỳ",
    "ngon hơn",
    "không thơm"
  ],
  "has_cta": "true",
  "highlight_phrases": [
    "Đây nha mọi người, cái màu của nó rất là đậm và mình thấy khá là nhiều phẩm màu bên trong.",
    "Về mùi thì mình thấy rất là giống. Nhưng mà cái này nó sẽ thiên về ngọt.",
    "Bò húc uống khác hẳn, ngon hơn rất là nhiều mọi người ạ."
  ],
  "hook_content": "Trải nghiệm gói bột pha bò húc.",
  "hook_type": [
    "Vào thẳng vấn đề"
  ],
  "pacing": [
    "Nhanh"
  ],
  "structure_style": [
    "So sánh",
    "Chia sẻ trải nghiệm cá nhân"
  ],
  "summarization": "Video trải nghiệm và so sánh bột pha bò húc với bò húc thật. Người nói nhận thấy bột pha có màu đậm, vị ngọt hơn và mùi hóa học hơn so với bò húc thật. Kết luận, bò húc thật vẫn ngon hơn và bột pha chỉ nên uống cho vui.",
  "tone_of_voice": [
    "Thân thiện",
    "Chân thành"
  ]
}