{
  "categories": [
    "Review sản phẩm ăn uống"
  ],
  "audience_target": [
    "Người thích ăn vặt, đồ ngọt",
    "Người nội trợ, yêu thích nấu ăn tại nhà"
  ],
  "body_analysis": [
    {
      "step": "Giới thiệu giỏ quà Tết",
      "comment": "Giá cả hợp lý, nhiều món."
    },
    {
      "step": "Review các món trong giỏ quà",
      "comment": "Đánh giá chi tiết từng sản phẩm."
    },
    {
      "step": "Tính toán giá trị thực tế của giỏ quà",
      "comment": "So sánh giá mua lẻ và giá combo."
    },
    {
      "step": "Đánh giá chung",
      "comment": "Nhận xét về sự tiện lợi và tiết kiệm khi mua giỏ quà."
    }
  ],
  "content_style": [
    "Đời thường",
    "Nhanh gọn"
  ],
  "cta_content": [],
  "cta_type": [],
  "emotion_keywords": [
    "ngon",
    "béo",
    "thơm",
    "ok la",
    "hợp lý",
    "xịn",
    "lời"
  ],
  "has_cta": "false",
  "highlight_phrases": [
    "Trời ơi tôi nói mọi người nó quá trời quá đất luôn.",
    "Đây là lần đầu tiên trong chuỗi series quà Tết của tôi mà tôi thấy lời nha."
  ],
  "hook_content": "Check giá giỏ quà Tết của siêu thị Emart 499.000.",
  "hook_type": [
    "Vào thẳng vấn đề"
  ],
  "pacing": [
    "Nhanh"
  ],
  "structure_style": [
    "Mô tả đặc điểm",
    "Chia sẻ trải nghiệm cá nhân"
  ],
  "summarization": "Video review giỏ quà Tết tại siêu thị Emart với giá 499.000 đồng. Người bán giới thiệu chi tiết từng món trong giỏ quà, so sánh giá cả và đánh giá tính tiện lợi, tiết kiệm khi mua combo. Video kết luận rằng đây là một lựa chọn có lợi cho người mua.",
  "tone_of_voice": [
    "Hào hứng",
    "Thân thiện"
  ]
}