{
  "categories": [
    "Nấu ăn",
    "Review món ăn"
  ],
  "audience_target": [
    "Người trẻ (Gen Z)",
    "Người nội trợ, yêu thích nấu ăn tại nhà",
    "Người thích khám phá ẩm thực tại địa phương"
  ],
  "body_analysis": [
    {
      "step": "Chuẩn bị nguyên liệu",
      "comment": "Giới thiệu nguyên liệu bạch tuộc và bông lục bình."
    },
    {
      "step": "Sơ chế bạch tuộc",
      "comment": "Gỡ và rửa sơ bạch tuộc."
    },
    {
      "step": "Ướp bạch tuộc",
      "comment": "Ướp bạch tuộc với sa tế và ngũ vị hương."
    },
    {
      "step": "Nướng bạch tuộc",
      "comment": "Nướng bạch tuộc trên lò nướng."
    },
    {
      "step": "Pha muối tiêu",
      "comment": "Pha muối tiêu chanh ớt."
    },
    {
      "step": "Thưởng thức bạch tuộc nướng",
      "comment": "Trình bày và ăn thử bạch tuộc nướng."
    },
    {
      "step": "Giới thiệu nước bao tử",
      "comment": "Giới thiệu loại nước uống quen thuộc."
    },
    {
      "step": "Ăn kèm bông lục bình",
      "comment": "Ăn bạch tuộc nướng kèm bông lục bình."
    }
  ],
  "content_style": [
    "Đời thường",
    "Gen Z",
    "Nhanh gọn"
  ],
  "cta_content": [
    "ai biết cái món gì làm từ lục bình thì chỉ cho mình biết với ha."
  ],
  "cta_type": [
    "Bình luận",
    "Chia sẻ công thức"
  ],
  "emotion_keywords": [
    "ngon",
    "thèm",
    "cay cay",
    "giòn giòn",
    "cuốn",
    "bắt vị",
    "yêu thích"
  ],
  "has_cta": "true",
  "highlight_phrases": [
    "bạch tuột nướng sa tế món này hơi bị ngon nhe",
    "Mà phải đúng là cái loại bạch tuột này thì ăn nó mới ngon.",
    "Cái bông lục bình này thì ăn hơi bị ngon nha.",
    "Trong tất cả các món nướng thì cái bạch tuột nướng chắc là cái món mà mình yêu thích nhất.",
    "Kiểu nướng sa tế thì ăn nó cay cay mà cái chân bạch tuột nó giòn giòn nữa nên thành ra là cái món này ăn cuốn dữ thần lắm.",
    "Cái bông này mà chấm với cá kho hay là lẩu mắm là dính dữ lắm."
  ],
  "hook_content": "Tôi nói thèm bạch tuột từ hôm qua tới bây giờ nên là sáng nay phải chạy ra chợ kiếm cho bằng được.",
  "hook_type": [
    "Vào thẳng vấn đề"
  ],
  "pacing": [
    "Nhanh"
  ],
  "structure_style": [
    "Chia sẻ trải nghiệm cá nhân",
    "Hướng dẫn"
  ],
  "summarization": "Video chia sẻ về món bạch tuộc nướng sa tế và trải nghiệm đi chợ, hái bông lục bình để ăn kèm. Người làm video thể hiện sự yêu thích món bạch tuộc nướng và chia sẻ cách chế biến đơn giản tại nhà. Cuối video, người này cũng giới thiệu loại nước uống quen thuộc và hỏi ý kiến về các món ăn từ lục bình.",
  "tone_of_voice": [
    "Thân thiện",
    "Hào hứng"
  ]
}