{
  "categories": [
    "Mukbang"
  ],
  "audience_target": [
    "Người trẻ (Gen Z)",
    "Người thích ăn vặt, đồ ngọt",
    "Người thích khám phá ẩm thực tại địa phương"
  ],
  "body_analysis": [
    {
      "step": "Giới thiệu món ăn",
      "comment": "Giới thiệu chem chép hấp xả ớt lá chanh và nước mắm chua ngọt tự làm."
    },
    {
      "step": "Uống nước",
      "comment": "Uống nước trước khi ăn."
    },
    {
      "step": "Ăn thử và cảm nhận",
      "comment": "Lần đầu ăn chem chép, cảm nhận vị giòn ngọt và chia sẻ trải nghiệm tìm mua nguyên liệu."
    },
    {
      "step": "Đánh giá và so sánh",
      "comment": "So sánh độ ngon giữa các con chem chép khác nhau và cách chế biến."
    },
    {
      "step": "Gợi ý ăn kèm",
      "comment": "Gợi ý các loại rau củ ăn kèm với chem chép."
    },
    {
      "step": "Kết luận",
      "comment": "Nhận xét về độ cuốn hút của món ăn và chất lượng sản phẩm."
    }
  ],
  "content_style": [
    "Đời thường",
    "Sáng tạo"
  ],
  "cta_content": [
    "Ở đây có bạn nào ăn cham chép chưa? Comment cho vàng biết với nha.",
    "Nếu mà bạn muốn bạn múc ban món gì thì cứ comment ở bên dưới cho bạn biết nha."
  ],
  "cta_type": [
    "Bình luận"
  ],
  "emotion_keywords": [
    "ngon",
    "ngọt",
    "cuốn"
  ],
  "has_cta": "true",
  "highlight_phrases": [
    "Ăn cái này bị cuốn á bạn ơi. Không có dừng lại được luôn.",
    "Những em mập mà trắng như vậy ăn vô vàng cảm thấy nó ngọt hơn.",
    "Trời ơi, ăn cái này cuốn quá bạn. Không dừng lại được luôn."
  ],
  "hook_content": "Hai bạn, theo yêu cầu của nhiều bạn đã comment cho vàng á thì hôm nay vàng sẽ múc ban tr cham chép nha.",
  "hook_type": [
    "Phản hồi bình luận"
  ],
  "pacing": [
    "Nhanh"
  ],
  "structure_style": [
    "Chia sẻ trải nghiệm cá nhân"
  ],
  "summarization": "Video mukbang chem chép hấp xả ớt của Tóc Vàng. Bạn chia sẻ trải nghiệm lần đầu ăn chem chép, cảm nhận hương vị và gợi ý các món ăn kèm. Video có nhiều cảm xúc tích cực và kêu gọi người xem bình luận.",
  "tone_of_voice": [
    "Hào hứng",
    "Thân thiện",
    "Chân thành"
  ]
}