{
  "categories": [
    "Nấu ăn"
  ],
  "audience_target": [
    "Học sinh, sinh viên",
    "Người nội trợ, yêu thích nấu ăn tại nhà",
    "Người thích ăn vặt, đồ ngọt",
    "Người trẻ (Gen Z)"
  ],
  "body_analysis": [
    {
      "step": "Giới thiệu món ăn",
      "comment": "Mô tả món ăn tủ của mình nhưng hay bị chê."
    },
    {
      "step": "Nguyên liệu",
      "comment": "Liệt kê nguyên liệu và giá cả."
    },
    {
      "step": "Sơ chế",
      "comment": "Hướng dẫn sơ chế bắp và xúc xích."
    },
    {
      "step": "Chiên xúc xích",
      "comment": "Chiên xúc xích cho đến khi xù lên."
    },
    {
      "step": "Xào bắp",
      "comment": "Xào bắp với tỏi phi thơm và trứng."
    },
    {
      "step": "Làm sốt",
      "comment": "Trộn nước sốt theo công thức và đảo cùng xúc xích."
    },
    {
      "step": "Hoàn thành",
      "comment": "Thêm hành lá và ngò, sẵn sàng để ăn."
    }
  ],
  "content_style": [
    "Đời thường",
    "Nhanh gọn"
  ],
  "cta_content": [],
  "cta_type": [],
  "emotion_keywords": [
    "ngon",
    "tiết kiệm"
  ],
  "has_cta": "false",
  "highlight_phrases": [
    "ăn ta nói nó vừa ngon mà nó vừa tiết kiệm",
    "nó xù lên y chang con mực"
  ],
  "hook_content": "nẫu nguyên bạn của tôi á cái món gì tôi làm á nó cũng khen hết trơn.",
  "hook_type": [
    "Kể chuyện"
  ],
  "pacing": [
    "Nhanh"
  ],
  "structure_style": [
    "Hướng dẫn"
  ],
  "summarization": "Video chia sẻ món ăn cứu đói sinh viên cuối tháng từ bắp và xúc xích. Người làm video hướng dẫn chi tiết cách sơ chế, chế biến và nêm nếm món ăn đơn giản này. Món ăn này vừa ngon vừa giúp tiết kiệm chi phí.",
  "tone_of_voice": [
    "Thân thiện",
    "Hài hước"
  ]
}