{
  "categories": [
    "Review quán ăn",
    "Review món ăn"
  ],
  "audience_target": [
    "Người trẻ (Gen Z)",
    "Người thích khám phá ẩm thực tại địa phương"
  ],
  "body_analysis": [
    {
      "step": "Giới thiệu quán phở",
      "comment": "Giới thiệu quán phở bò của chị Lan và sự nổi tiếng của quán."
    },
    {
      "step": "Gọi món",
      "comment": "Gọi một bát phở đế thăn nạm, nước béo nhiều hành và quẩy."
    },
    {
      "step": "Nhận xét về quán",
      "comment": "Nhấn mạnh sự vui vẻ của chủ quán và sự đông khách của quán."
    },
    {
      "step": "Giới thiệu về phở bò Nam Định",
      "comment": "Giới thiệu phở bò ở đây theo style Nam Định và mối liên hệ với phở bò Hương Hậu."
    },
    {
      "step": "Miêu tả món ăn",
      "comment": "Miêu tả phần đế thăn và diềm thăn của bò, nhấn mạnh độ ngon của nó."
    },
    {
      "step": "Đánh giá về bát phở",
      "comment": "Nhấn mạnh bát phở to và khẳng định phở là văn hóa phi vật thể."
    },
    {
      "step": "Mua thêm đồ ăn mang về",
      "comment": "Mua thêm một tái sốt mang về."
    },
    {
      "step": "Chào tạm biệt",
      "comment": "Chào tạm biệt và chúc chị Lan giữ gìn phong độ."
    },
    {
      "step": "Giới thiệu phở chị Lan",
      "comment": "Giới thiệu lại quán phở và mời em bé ăn."
    },
    {
      "step": "Cho em bé ăn phở",
      "comment": "Đưa em bé ăn phở và trêu đùa về việc em bé xúc động."
    }
  ],
  "content_style": [
    "Đời thường",
    "Nhanh gọn"
  ],
  "cta_content": [
    "Giới thiệu toàn thể anh em bà con nhá.",
    "Đây là phở chị Lăn chị Lan thôi.",
    "Rất là nổi tiếng ở trên gần phố nhá.",
    "Xin mời em bé ăn phi vật thể của nhân loại nhé."
  ],
  "cta_type": [
    "Ghé thăm địa điểm",
    "Chia sẻ"
  ],
  "emotion_keywords": [
    "thèm",
    "vui",
    "ngon",
    "xúc động",
    "cảm động"
  ],
  "has_cta": "true",
  "highlight_phrases": [
    "văn hóa phi vật thể của nhân loại",
    "ăn ở phở Lan thì cái món gì mà chẳng ngon",
    "văn hóa phi vật thể là phở đấy"
  ],
  "hook_content": "Em có muốn sáng nay làm một bát văn hóa phi vật thể của nhân loại không?",
  "hook_type": [
    "Đặt câu hỏi"
  ],
  "pacing": [
    "Nhanh"
  ],
  "structure_style": [
    "Chia sẻ trải nghiệm cá nhân",
    "Mô tả đặc điểm"
  ],
  "summarization": "Video giới thiệu quán phở bò Lan nổi tiếng ở Hà Nội, đặc biệt là món phở bò Nam Định. Người quay review hương vị phở, sự nhiệt tình của chủ quán và không khí quán xá. Cuối video, người quay mua thêm phở mang về cho em bé và trêu đùa.",
  "tone_of_voice": [
    "Hào hứng",
    "Thân thiện",
    "Hài hước"
  ]
}