{
  "categories": ["Review sản phẩm ăn uống", "Review món ăn", "Mukbang"],
  "audience_target": ["Người trẻ (Gen Z)", "Người thích ăn vặt, đồ ngọt"],
  "body_analysis": [],
  "content_style": ["Đời thường", "Nhanh gọn"],
  "cta_content": [],
  "cta_type": [],
  "emotion_keywords": ["phê"],
  "has_cta": "false",
  "highlight_phrases": ["bên ngoài thì giòn, bên trong thì phun thật luôn, chua chua ngọt ngọt cực kỳ phê"],
  "hook_content": "review cả thế giới kẹo sáp hình con chó.",
  "hook_type": ["Vào thẳng vấn đề"],
  "pacing": ["Nhanh"],
  "structure_style": ["Mô tả đặc điểm", "Chia sẻ trải nghiệm cá nhân"],
  "summarization": "Video review kẹo sáp hình con chó, mô tả lớp vỏ giòn và phần nhân phun bên trong có vị chua ngọt.",
  "tone_of_voice": ["Hào hứng"]
}