{
  "categories": [
    "Review sản phẩm ăn uống"
  ],
  "audience_target": [
    "Người trẻ (Gen Z)",
    "Người thích ăn vặt, đồ ngọt"
  ],
  "body_analysis": [
    {
      "step": "Giới thiệu sản phẩm",
      "comment": "Mở đầu bằng việc giới thiệu sản phẩm làm trắng răng tại nhà và đánh giá cao hiệu quả của nó."
    },
    {
      "step": "Ba lý do thích bộ kit",
      "comment": "Liệt kê những ưu điểm của bộ kit làm trắng răng, tập trung vào hiệu quả làm trắng, tính an toàn và giá cả phải chăng."
    },
    {
      "step": "Lý do ngừng dùng miếng dán",
      "comment": "So sánh với miếng dán trắng răng và đưa ra những nhược điểm khiến người dùng không hài lòng."
    },
    {
      "step": "So sánh với nha khoa",
      "comment": "So sánh với việc tẩy trắng răng tại nha khoa và đưa ra lý do lựa chọn sản phẩm tại nhà."
    },
    {
      "step": "Đánh giá chung",
      "comment": "Khẳng định trải nghiệm tốt nhất với sản phẩm hiện tại."
    }
  ],
  "content_style": [
    "Đời thường",
    "Nhanh gọn",
    "Chi tiết"
  ],
  "cta_content": [
    "Rất là highly recommend mọi người nha"
  ],
  "cta_type": [
    "Truy cập link sản phẩm"
  ],
  "emotion_keywords": [
    "thích",
    "ok la",
    "rẻ",
    "xinh xắn",
    "tiện lợi",
    "hời",
    "highly recommend"
  ],
  "has_cta": "true",
  "highlight_phrases": [
    "răng sẽ trắng lên trông thấy á",
    "răng mình đã trắng bật lên ba tông",
    "không hề ê buốt xíu nào",
    "trắng không đều kiểu bị loang lổ á",
    "thật sự nó là một cơn ác mộng mang tên ê buốt"
  ],
  "hook_content": "sử dụng cái miếng dán này là răng sẽ trắng lên trông thấy á, không nha.",
  "hook_type": [
    "Gây tò mò",
    "Cho thấy kết quả trước"
  ],
  "pacing": [
    "Nhanh"
  ],
  "structure_style": [
    "Chia sẻ trải nghiệm cá nhân",
    "So sánh"
  ],
  "summarization": "Video review bộ kit làm trắng răng tại nhà Smiley Extra White, so sánh với miếng dán trắng răng và phương pháp tẩy trắng tại nha khoa. Người nói chia sẻ trải nghiệm cá nhân và đánh giá cao hiệu quả, tính an toàn và giá cả của sản phẩm. Cuối video có lời kêu gọi mua sản phẩm.",
  "tone_of_voice": [
    "Hào hứng",
    "Thân thiện",
    "Chân thành"
  ]
}