{
  "categories": [
    "Review quán ăn",
    "Review món ăn"
  ],
  "audience_target": [
    "Học sinh, sinh viên",
    "Người đi làm, dân văn phòng",
    "Người trẻ (Gen Z)",
    "Người thích khám phá ẩm thực tại địa phương"
  ],
  "body_analysis": [
    {
      "step": "Giới thiệu tiệm cơm văn phòng",
      "comment": "Quán quen thuộc của người review."
    },
    {
      "step": "Các tiêu chí lựa chọn quán",
      "comment": "Đầy đặn, giá cả phải chăng, có mã giảm giá."
    },
    {
      "step": "Review cơm trứng phủ",
      "comment": "Món đặc trưng nhưng hơi nhạt, cần thêm sốt."
    },
    {
      "step": "Review cơm cà ri gà chiên khổng lồ",
      "comment": "Cà ri thơm kiểu Nhật, gà không bị khô."
    },
    {
      "step": "Review cơm thịt heo nướng khói trứng onsen",
      "comment": "Thịt ba chỉ nướng khói kết hợp trứng onsen béo ngậy."
    },
    {
      "step": "Review gà má đùi sốt",
      "comment": "Gà mềm, thêm sốt ngon hơn."
    },
    {
      "step": "Đánh giá chung về Omu Ome",
      "comment": "Quán cơm online ngon, bổ, rẻ, phù hợp với sinh viên, dân văn phòng và người lười nấu cơm."
    },
    {
      "step": "Thông tin về cách đặt hàng mới",
      "comment": "Đặt qua hotline hoặc fanpage FlyyChef để có nhiều ưu đãi."
    }
  ],
  "content_style": [
    "Đời thường",
    "Nhanh gọn"
  ],
  "cta_content": [
    "Có cả free ship trong bán kính 3 cây nữa, mọi người tham khảo cách đặt hàng mới này cho những bữa trưa bữa tối không biết ăn gì nha."
  ],
  "cta_type": [
    "Ghé thăm địa điểm"
  ],
  "emotion_keywords": [
    "ngon",
    "vừa",
    "thơm",
    "mềm",
    "ẩm",
    "béo ngậy",
    "giải ngấy"
  ],
  "has_cta": "true",
  "highlight_phrases": [
    "cơm gà chiên khổng lồ",
    "cắn cũng khá ngập răng đấy",
    "vị béo ngậy của trứng onsen nó lại rất hợp với cái mùi nướng khói của thịt heo"
  ],
  "hook_content": "Đây là một cái tiệm cơm văn phòng mà mình gọi nhiều nhất từ trước đến nay.",
  "hook_type": [
    "Vào thẳng vấn đề"
  ],
  "pacing": [
    "Nhanh"
  ],
  "structure_style": [
    "Chia sẻ trải nghiệm cá nhân",
    "Mô tả đặc điểm"
  ],
  "summarization": "Video review tiệm cơm văn phòng Omu Ome với các món ăn được yêu thích như cơm trứng phủ, cơm cà ri gà chiên khổng lồ, cơm thịt heo nướng khói trứng onsen và gà má đùi sốt. Người review đánh giá quán ngon, bổ, rẻ và chia sẻ cách đặt hàng mới để được ưu đãi.",
  "tone_of_voice": [
    "Thân thiện",
    "Chân thành"
  ]
}