{
  "categories": [
    "Review món ăn"
  ],
  "audience_target": [
    "Học sinh, sinh viên",
    "Người trẻ (Gen Z)",
    "Người thích ăn vặt, đồ ngọt",
    "Người thích khám phá ẩm thực tại địa phương"
  ],
  "body_analysis": [
    {
      "step": "Giới thiệu món ăn",
      "comment": "Món chân gà mít trứng non lòng đào sốt Thái được giới thiệu là món khoái khẩu, ăn nhiều lần trong tháng."
    },
    {
      "step": "Chuẩn bị nguyên liệu",
      "comment": "Hướng dẫn mua chân gà, trứng non, xoài, rau răm, sả."
    },
    {
      "step": "Sử dụng sốt Thái",
      "comment": "Giới thiệu và sử dụng sốt Thái của anh hai Thái Châu 0808, muối ớt đỏ để trộn và chấm."
    },
    {
      "step": "Đánh giá món ăn",
      "comment": "Mô tả món ăn hấp dẫn với trứng hồng đào tan chảy, chân gà giòn, sốt đậm đà, xoài chua chua."
    },
    {
      "step": "Giới thiệu sản phẩm",
      "comment": "Nhấn mạnh chất lượng sản phẩm nhà làm của anh hai Thái Châu 0808."
    }
  ],
  "content_style": [
    "Đời thường",
    "Nhanh gọn"
  ],
  "cta_content": [
    "Còn ai mà muốn mua muối ớt đỏ, sốt Thái và muối chấm trái cây thì kiếm anh hai tôi Thái Châu 0808 nhen.",
    "Giờ thì mời mọi người ăn chung với tôi nhen."
  ],
  "cta_type": [
    "Ăn cùng",
    "Truy cập trang cá nhân"
  ],
  "emotion_keywords": [
    "hấp dẫn",
    "ngon lành",
    "đỉnh",
    "mê",
    "béo ngậy",
    "ngon bá cháy"
  ],
  "has_cta": "true",
  "highlight_phrases": [
    "Siêu hấp dẫn ngon lành mà làm thì phải gọi là cực kỳ lẹ luôn.",
    "tinh hoa hội tụ, vị thì đậm đà nên đem trộn một cái ăn vô sốc liền tại nó quá đỉnh",
    "chân gà thì giòn thật sặt, thấm đẫm sốt đậm đà cay thơm, quất thêm miếng trứng non béo ngậy rồi xoài chua chua đúng là ngon bá cháy mọi người ơi"
  ],
  "hook_content": "Một món khoái khẩu mà một tháng mọi người phải ăn ba bốn lần mới chịu là món gì? Tôi thì chắc chắn là món chân gà mít trứng non lòng đào sốt Thái rồi.",
  "hook_type": [
    "Đặt câu hỏi",
    "Vào thẳng vấn đề"
  ],
  "pacing": [
    "Nhanh"
  ],
  "structure_style": [
    "Hướng dẫn",
    "Mô tả đặc điểm",
    "Chia sẻ trải nghiệm cá nhân"
  ],
  "summarization": "Video giới thiệu món chân gà mít trứng non lòng đào sốt Thái, hướng dẫn cách làm nhanh gọn với các nguyên liệu dễ kiếm. Người nói đặc biệt nhấn mạnh vào sốt Thái và muối ớt đỏ của anh hai Thái Châu 0808, mô tả món ăn có vị ngon hấp dẫn, đậm đà.",
  "tone_of_voice": [
    "Hào hứng",
    "Thân thiện"
  ]
}