{
   "stats": {
      "diggCount": 0,
      "followerCount": 1400000,
      "followingCount": 9,
      "friendCount": 9,
      "heart": 20000000,
      "heartCount": 20000000,
      "videoCount": 355
   },
   "user": {
      "avatarLarger": "https://p16-sign-sg.tiktokcdn.com/tos-alisg-avt-0068/529e005e6e5e8cb05228e1da0eadeb0d~tplv-tiktokx-cropcenter:1080:1080.jpeg?dr=14579&refresh_token=c6b04f81&x-expires=1742547600&x-signature=sxaJb7T0IwoaDB%2BncMDWhsHUHDY%3D&t=4d5b0474&ps=13740610&shp=a5d48078&shcp=81f88b70&idc=my",
      "avatarMedium": "https://p16-sign-sg.tiktokcdn.com/tos-alisg-avt-0068/529e005e6e5e8cb05228e1da0eadeb0d~tplv-tiktokx-cropcenter:720:720.jpeg?dr=14579&refresh_token=1f3be4a5&x-expires=1742547600&x-signature=Ll1juzsRoPa1Z13fWeD4invpRns%3D&t=4d5b0474&ps=13740610&shp=a5d48078&shcp=81f88b70&idc=my",
      "avatarThumb": "https://p16-sign-sg.tiktokcdn.com/tos-alisg-avt-0068/529e005e6e5e8cb05228e1da0eadeb0d~tplv-tiktokx-cropcenter:100:100.jpeg?dr=14579&refresh_token=ecfa4b58&x-expires=1742547600&x-signature=S4sD2UWwHzYt0A%2Bcg162akfSQYA%3D&t=4d5b0474&ps=13740610&shp=a5d48078&shcp=81f88b70&idc=my",
      "bioLink": {
         "link": "https://www.tiktok.com/@huynhanhtuanofficial",
         "risk": 0
      },
      "canExpPlaylist": true,
      "commentSetting": 0,
      "commerceUserInfo": {
         "commerceUser": false
      },
      "downloadSetting": 3,
      "duetSetting": 0,
      "followingVisibility": 2,
      "ftc": false,
      "id": "6806417388361516033",
      "isADVirtual": false,
      "isEmbedBanned": false,
      "nickNameModifyTime": 1688613875,
      "nickname": "Di\u1ec5n vi\u00ean Hu\u1ef3nh Anh Tu\u1ea5n",
      "openFavorite": false,
      "privateAccount": false,
      "profileEmbedPermission": 1,
      "profileTab": {
         "showPlayListTab": false
      },
      "relation": 0,
      "secUid": "MS4wLjABAAAAa-rR03m4AtuaYOz-BcyxE2lxVB8HCfqJwQ5gVT72EphB5zq9qhzHdCdaf3QfJrl1",
      "secret": false,
      "signature": "Tiktok Ch\u00ednh Ch\u1ee7 c\u1ee7a Tu\u1ea5n\u2705 \u0111\u01b0\u1eddng link k\u00eanh ph\u1ee5 b\u00ean d\u01b0\u1edbi\ud83d\udc47",
      "stitchSetting": 0,
      "ttSeller": false,
      "uniqueId": "huynhanhtuan_dienvien",
      "verified": false
   }
}